{
  "posts": [
    {
      "id": 1,
      "title": "json-server",
      "author": "typicode"
    }
  ],
  "signUpUsers": [
    {
      "fullname": "marouane",
      "email": "marouane",
      "password": "123",
      "statcode": "marouane",
      "id": 5
    },
    {
      "fullname": "salam",
      "email": "salam@",
      "password": "123",
      "statcode": "123",
      "id": 6
    },
    {
      "fullname": "admin",
      "email": "m@gmail",
      "password": "1234",
      "statcode": "1234",
      "id": 7
    }
  ],
  "profile": {
    "name": "typicode"
  }
}
